nonebot_plugin_deltaforce_simulator/__init__.py
nonebot_plugin_deltaforce_simulator/config.py
nonebot_plugin_deltaforce_simulator/container_configs.json
nonebot_plugin_deltaforce_simulator/gen_result.py
nonebot_plugin_deltaforce_simulator/resource/armor.json
nonebot_plugin_deltaforce_simulator/resource/bag.json
nonebot_plugin_deltaforce_simulator/resource/bxx.png
nonebot_plugin_deltaforce_simulator/resource/chest.json
nonebot_plugin_deltaforce_simulator/resource/cnw.png
nonebot_plugin_deltaforce_simulator/resource/collection.json
nonebot_plugin_deltaforce_simulator/resource/fail.jpg
nonebot_plugin_deltaforce_simulator/resource/gjcwx.png
nonebot_plugin_deltaforce_simulator/resource/helmet.json
nonebot_plugin_deltaforce_simulator/resource/hkcwx.png
nonebot_plugin_deltaforce_simulator/resource/nw.png
nonebot_plugin_deltaforce_simulator/resource/success.png
nonebot_plugin_deltaforce_simulator/resource/xbxx.png
nonebot_plugin_deltaforce_simulator/resource/Yahei.ttf
nonebot_plugin_deltaforce_simulator-1.0.0.dist-info/METADATA
nonebot_plugin_deltaforce_simulator-1.0.0.dist-info/WHEEL
nonebot_plugin_deltaforce_simulator-1.0.0.dist-info/RECORD
