Metadata-Version: 2.1
Name: nonebot-plugin-deltaforce-simulator
Version: 1.0.0
Summary: 适用于nonebot的三角洲鼠鼠偷吃模拟器（开容器模拟器）机器人插件
License: MIT
Author: Alpaca
Author-email: 202396298@qq.com
Requires-Python: >=3.8,<4.0
Classifier: License :: OSI Approved :: MIT License
Classifier: Programming Language :: Python :: 3
Classifier: Programming Language :: Python :: 3.8
Classifier: Programming Language :: Python :: 3.9
Classifier: Programming Language :: Python :: 3.10
Classifier: Programming Language :: Python :: 3.11
Classifier: Programming Language :: Python :: 3.12
Classifier: Programming Language :: Python :: 3.13
Requires-Dist: httpx (>=0.27.0)
Requires-Dist: nonebot-adapter-onebot (>=2.2.1,<3.0.0)
Requires-Dist: nonebot-plugin-send-anything-anywhere (>=0.7.1,<0.8.0)
Requires-Dist: nonebot2 (>=2.2.0,<3.0.0)
Requires-Dist: nonebot_plugin_userinfo (>=0.2.6,<0.3.0)
Requires-Dist: pillow (>=10.0)
